pytorchtools/__init__.py
pytorchtools/pytorchtools.py
pytorchtools-0.0.2.dist-info/AUTHORS.rst
pytorchtools-0.0.2.dist-info/LICENSE
pytorchtools-0.0.2.dist-info/METADATA
pytorchtools-0.0.2.dist-info/WHEEL
pytorchtools-0.0.2.dist-info/top_level.txt
pytorchtools-0.0.2.dist-info/RECORD
