Metadata-Version: 2.1
Name: pytorchtools
Version: 0.0.2
Summary: Pytorch Tools
Home-page: https://github.com/francisco-perez-sorrosal/pytorchtools
Author: Francisco Perez-Sorrosal
Author-email: fperezsorrosal@gmail.com
License: Apache Software License 2.0
Keywords: pytorchtools
Platform: UNKNOWN
Classifier: Development Status :: 2 - Pre-Alpha
Classifier: Intended Audience :: Developers
Classifier: License :: OSI Approved :: Apache Software License
Classifier: Natural Language :: English
Classifier: Programming Language :: Python :: 2
Classifier: Programming Language :: Python :: 2.7
Classifier: Programming Language :: Python :: 3
Classifier: Programming Language :: Python :: 3.4
Classifier: Programming Language :: Python :: 3.5
Classifier: Programming Language :: Python :: 3.6
Classifier: Programming Language :: Python :: 3.7
